barcodes_uc/__init__.py
barcodes_uc/barcodes/__init__.py
barcodes_uc/barcodes/__main__.py
barcodes_uc/qrcodes/__init__.py
barcodes_uc/qrcodes/__main__.py
barcodes_uc/qrcodes/qrgenerator.py
barcodes_uc/qrcodes/qrutils.py
data/GF256.csv
data/alignment_locations.csv
data/capabilities.csv
data/error_correction_table.csv
data/format_table.csv
data/version_table.csv
requirements.txt
barcodes_uc-0.9.0.dist-info/METADATA
barcodes_uc-0.9.0.dist-info/WHEEL
barcodes_uc-0.9.0.dist-info/entry_points.txt
barcodes_uc-0.9.0.dist-info/RECORD
