Metadata-Version: 2.1
Name: barcodes-uc
Version: 0.9.0
Summary: A library to generate barcodes
Home-page: https://github.com/Parzival1918/barcodes-uc
Author: Pedro Juan Royo
Author-email: pedro.juan.royo@gmail.com
Requires-Python: >=3.9,<4.0
Classifier: Programming Language :: Python :: 3
Classifier: Programming Language :: Python :: 3.9
Classifier: Programming Language :: Python :: 3.10
Classifier: Programming Language :: Python :: 3.11
Requires-Dist: aenum (>=3.1.15,<4.0.0)
Requires-Dist: numpy (>=1.25.1,<2.0.0)
Requires-Dist: pandas (>=2.0.3,<3.0.0)
Requires-Dist: pillow (>=10.0.0,<11.0.0)
Project-URL: Repository, https://github.com/Parzival1918/barcodes-uc
